<?xml version="1.0" encoding="UTF-8"?>
<databaseChangeLog
        xmlns="http://www.liquibase.org/xml/ns/dbchangelog"
        xmlns:xsi="http://www.w3.org/2001/XMLSchema-instance"
        xsi:schemaLocation="http://www.liquibase.org/xml/ns/dbchangelog
                      http://www.liquibase.org/xml/ns/dbchangelog/dbchangelog-4.5.xsd"
        objectQuotingStrategy="QUOTE_ONLY_RESERVED_WORDS">

<changeSet id="1" author="SellStore" context="!cuba">


    <insert tableName="USER_" dbms="oracle, mysql, mariadb">
        <column name="ID" value="050d3958-641b-356e-3cc8-493c0986f4ec"/>
        <column name="VERSION" value="1"/>
        <column name="USERNAME" value="Mug"/>
        <column name="PASSWORD" value="{noop}1"/>
        <column name="FIRST_NAME" value="Muhammed"/>
        <column name="LAST_NAME" value="Abduru"/>
        <column name="EMAIL" value="muhab@ret.company"/>
        <column name="ACTIVE" valueBoolean="true"/>
    </insert>

    <insert tableName="USER_" dbms="oracle, mysql, mariadb">
        <column name="ID" value="be2cf48b-f84b-d0a6-1627-64d32f9db432"/>
        <column name="VERSION" value="1"/>
        <column name="USERNAME" value="Eugene"/>
        <column name="PASSWORD" value="{noop}1"/>
        <column name="FIRST_NAME" value="Евгений"/>
        <column name="LAST_NAME" value="Баев"/>
        <column name="EMAIL" value="Ebaev2001@ret.company"/>
        <column name="ACTIVE" valueBoolean="true"/>
    </insert>

    <insert tableName="USER_" dbms="oracle, mysql, mariadb">
        <column name="ID" value="e293213b-a947-7251-059a-fc2650602885"/>
        <column name="VERSION" value="1"/>
        <column name="USERNAME" value="Dmito"/>
        <column name="PASSWORD" value="{noop}1"/>
        <column name="FIRST_NAME" value="Dmitro"/>
        <column name="LAST_NAME" value="Hasahash"/>
        <column name="EMAIL" value="dmito@ret.company"/>
        <column name="ACTIVE" valueBoolean="true"/>
    </insert>

</changeSet>
</databaseChangeLog>